dictionary/__init__.py
dictionary/dictionary.py
cs453_project_mert_yildirim-2.0.1.dist-info/METADATA
cs453_project_mert_yildirim-2.0.1.dist-info/WHEEL
cs453_project_mert_yildirim-2.0.1.dist-info/top_level.txt
cs453_project_mert_yildirim-2.0.1.dist-info/RECORD
