Metadata-Version: 2.1
Name: cs453-project-mert-yildirim
Version: 2.0.1
Summary: UNKNOWN
Author: Mert Yildirim
License: UNKNOWN
Platform: UNKNOWN
Requires-Python: >=3.8
Requires-Dist: requests (>=2.23.0)
